generator/__init__.py
generator/pagen.py
Pagen-0.0.1.dist-info/LICENSE
Pagen-0.0.1.dist-info/METADATA
Pagen-0.0.1.dist-info/WHEEL
Pagen-0.0.1.dist-info/top_level.txt
Pagen-0.0.1.dist-info/RECORD
