Metadata-Version: 2.1
Name: Pagen
Version: 0.0.1
Summary: Generates random password
Home-page: UNKNOWN
Author: Mohammad Mahfuz Rahman
Author-email: mahfuzrahman038@gmail.com
License: UNKNOWN
Keywords: Password,generator,bruteforce
Platform: UNKNOWN
Classifier: Development Status :: 1 - Planning
Classifier: Intended Audience :: Developers
Classifier: Programming Language :: Python :: 3
Classifier: Operating System :: Microsoft :: Windows
License-File: LICENSE
Requires-Dist: commandtaker
Requires-Dist: wlanpass
